{
    "image": "assets/letters\\M\\m_0.jpg",
    "letter": "M",
    "entry_point": [
        5,
        395
    ],
    "exit_point": [
        278,
        299
    ],
    "entry_angle": 14.036243467926479,
    "exit_angle": -78.69006752597979,
    "average_width": 5.821379661560059,
    "brush_size": 5,
    "flow_points": [
        [
            5,
            395
        ],
        [
            6,
            396
        ],
        [
            6,
            396
        ],
        [
            8,
            396
        ],
        [
            9,
            396
        ],
        [
            9,
            396
        ],
        [
            11,
            396
        ],
        [
            12,
            396
        ],
        [
            14,
            396
        ],
        [
            16,
            396
        ],
        [
            18,
            396
        ],
        [
            20,
            396
        ],
        [
            21,
            396
        ],
        [
            23,
            396
        ],
        [
            24,
            396
        ],
        [
            24,
            395
        ],
        [
            25,
            395
        ],
        [
            27,
            393
        ],
        [
            29,
            391
        ],
        [
            32,
            390
        ],
        [
            33,
            390
        ],
        [
            33,
            389
        ],
        [
            36,
            388
        ],
        [
            37,
            387
        ],
        [
            38,
            386
        ],
        [
            39,
            385
        ],
        [
            39,
            384
        ],
        [
            40,
            384
        ],
        [
            40,
            383
        ],
        [
            41,
            382
        ],
        [
            41,
            381
        ],
        [
            41,
            381
        ],
        [
            41,
            379
        ],
        [
            41,
            379
        ],
        [
            41,
            378
        ],
        [
            41,
            377
        ],
        [
            42,
            374
        ],
        [
            43,
            372
        ],
        [
            45,
            370
        ],
        [
            45,
            369
        ],
        [
            46,
            368
        ],
        [
            46,
            368
        ],
        [
            46,
            366
        ],
        [
            46,
            363
        ],
        [
            47,
            362
        ],
        [
            47,
            360
        ],
        [
            47,
            359
        ],
        [
            48,
            358
        ],
        [
            49,
            356
        ],
        [
            49,
            354
        ],
        [
            49,
            354
        ],
        [
            49,
            353
        ],
        [
            51,
            351
        ],
        [
            51,
            349
        ],
        [
            51,
            348
        ],
        [
            51,
            346
        ],
        [
            51,
            345
        ],
        [
            51,
            344
        ],
        [
            52,
            343
        ],
        [
            53,
            342
        ],
        [
            54,
            340
        ],
        [
            55,
            338
        ],
        [
            55,
            338
        ],
        [
            57,
            336
        ],
        [
            57,
            335
        ],
        [
            57,
            333
        ],
        [
            58,
            329
        ],
        [
            59,
            329
        ],
        [
            60,
            326
        ],
        [
            61,
            324
        ],
        [
            63,
            323
        ],
        [
            64,
            321
        ],
        [
            66,
            317
        ],
        [
            68,
            314
        ],
        [
            68,
            313
        ],
        [
            70,
            312
        ],
        [
            71,
            309
        ],
        [
            72,
            308
        ],
        [
            73,
            307
        ],
        [
            74,
            306
        ],
        [
            75,
            303
        ],
        [
            76,
            303
        ],
        [
            76,
            302
        ],
        [
            77,
            302
        ],
        [
            77,
            301
        ],
        [
            78,
            300
        ],
        [
            83,
            298
        ],
        [
            83,
            297
        ],
        [
            86,
            296
        ],
        [
            87,
            295
        ],
        [
            92,
            296
        ],
        [
            94,
            299
        ],
        [
            94,
            301
        ],
        [
            95,
            305
        ],
        [
            96,
            305
        ],
        [
            96,
            305
        ],
        [
            96,
            306
        ],
        [
            96,
            308
        ],
        [
            97,
            310
        ],
        [
            97,
            312
        ],
        [
            97,
            313
        ],
        [
            97,
            315
        ],
        [
            98,
            318
        ],
        [
            98,
            319
        ],
        [
            99,
            320
        ],
        [
            99,
            322
        ],
        [
            100,
            324
        ],
        [
            100,
            326
        ],
        [
            102,
            330
        ],
        [
            102,
            333
        ],
        [
            104,
            336
        ],
        [
            105,
            340
        ],
        [
            107,
            343
        ],
        [
            109,
            346
        ],
        [
            111,
            349
        ],
        [
            112,
            352
        ],
        [
            113,
            355
        ],
        [
            114,
            358
        ],
        [
            115,
            360
        ],
        [
            116,
            362
        ],
        [
            116,
            362
        ],
        [
            117,
            363
        ],
        [
            117,
            365
        ],
        [
            118,
            366
        ],
        [
            118,
            367
        ],
        [
            119,
            368
        ],
        [
            121,
            371
        ],
        [
            121,
            373
        ],
        [
            122,
            374
        ],
        [
            123,
            376
        ],
        [
            125,
            380
        ],
        [
            127,
            383
        ],
        [
            129,
            385
        ],
        [
            129,
            386
        ],
        [
            131,
            388
        ],
        [
            133,
            391
        ],
        [
            135,
            391
        ],
        [
            135,
            392
        ],
        [
            135,
            392
        ],
        [
            135,
            394
        ],
        [
            135,
            394
        ],
        [
            136,
            395
        ],
        [
            137,
            395
        ],
        [
            139,
            397
        ],
        [
            141,
            398
        ],
        [
            141,
            399
        ],
        [
            142,
            400
        ],
        [
            144,
            400
        ],
        [
            145,
            402
        ],
        [
            146,
            402
        ],
        [
            147,
            403
        ],
        [
            147,
            404
        ],
        [
            148,
            404
        ],
        [
            149,
            404
        ],
        [
            150,
            404
        ],
        [
            151,
            404
        ],
        [
            151,
            404
        ],
        [
            153,
            404
        ],
        [
            153,
            404
        ],
        [
            154,
            404
        ],
        [
            155,
            404
        ],
        [
            156,
            404
        ],
        [
            157,
            404
        ],
        [
            159,
            402
        ],
        [
            159,
            401
        ],
        [
            160,
            400
        ],
        [
            160,
            399
        ],
        [
            160,
            399
        ],
        [
            160,
            398
        ],
        [
            160,
            397
        ],
        [
            160,
            396
        ],
        [
            160,
            394
        ],
        [
            161,
            393
        ],
        [
            161,
            391
        ],
        [
            161,
            389
        ],
        [
            161,
            388
        ],
        [
            161,
            386
        ],
        [
            161,
            385
        ],
        [
            161,
            384
        ],
        [
            161,
            382
        ],
        [
            161,
            381
        ],
        [
            161,
            379
        ],
        [
            161,
            377
        ],
        [
            161,
            376
        ],
        [
            161,
            375
        ],
        [
            161,
            373
        ],
        [
            161,
            373
        ],
        [
            161,
            371
        ],
        [
            161,
            370
        ],
        [
            161,
            369
        ],
        [
            161,
            366
        ],
        [
            161,
            365
        ],
        [
            161,
            364
        ],
        [
            161,
            361
        ],
        [
            161,
            360
        ],
        [
            161,
            358
        ],
        [
            161,
            354
        ],
        [
            161,
            353
        ],
        [
            161,
            348
        ],
        [
            161,
            347
        ],
        [
            161,
            346
        ],
        [
            161,
            344
        ],
        [
            161,
            344
        ],
        [
            161,
            342
        ],
        [
            161,
            341
        ],
        [
            161,
            340
        ],
        [
            161,
            339
        ],
        [
            161,
            339
        ],
        [
            161,
            337
        ],
        [
            161,
            336
        ],
        [
            160,
            334
        ],
        [
            160,
            333
        ],
        [
            160,
            331
        ],
        [
            160,
            330
        ],
        [
            160,
            329
        ],
        [
            160,
            328
        ],
        [
            160,
            327
        ],
        [
            160,
            326
        ],
        [
            160,
            324
        ],
        [
            160,
            322
        ],
        [
            160,
            319
        ],
        [
            160,
            318
        ],
        [
            160,
            318
        ],
        [
            160,
            314
        ],
        [
            160,
            313
        ],
        [
            160,
            311
        ],
        [
            160,
            310
        ],
        [
            160,
            309
        ],
        [
            160,
            309
        ],
        [
            160,
            307
        ],
        [
            160,
            305
        ],
        [
            163,
            302
        ],
        [
            170,
            296
        ],
        [
            173,
            295
        ],
        [
            173,
            294
        ],
        [
            174,
            293
        ],
        [
            174,
            293
        ],
        [
            176,
            293
        ],
        [
            176,
            292
        ],
        [
            177,
            292
        ],
        [
            179,
            293
        ],
        [
            180,
            294
        ],
        [
            180,
            295
        ],
        [
            182,
            296
        ],
        [
            184,
            298
        ],
        [
            185,
            302
        ],
        [
            186,
            305
        ],
        [
            187,
            307
        ],
        [
            187,
            308
        ],
        [
            187,
            311
        ],
        [
            188,
            313
        ],
        [
            188,
            314
        ],
        [
            188,
            316
        ],
        [
            188,
            318
        ],
        [
            189,
            320
        ],
        [
            189,
            322
        ],
        [
            189,
            324
        ],
        [
            190,
            328
        ],
        [
            190,
            330
        ],
        [
            191,
            330
        ],
        [
            191,
            332
        ],
        [
            191,
            332
        ],
        [
            191,
            334
        ],
        [
            191,
            335
        ],
        [
            192,
            336
        ],
        [
            192,
            337
        ],
        [
            192,
            339
        ],
        [
            192,
            341
        ],
        [
            192,
            343
        ],
        [
            193,
            344
        ],
        [
            194,
            347
        ],
        [
            196,
            350
        ],
        [
            196,
            352
        ],
        [
            197,
            354
        ],
        [
            199,
            356
        ],
        [
            200,
            358
        ],
        [
            201,
            361
        ],
        [
            202,
            362
        ],
        [
            203,
            364
        ],
        [
            204,
            368
        ],
        [
            206,
            370
        ],
        [
            206,
            373
        ],
        [
            208,
            375
        ],
        [
            209,
            375
        ],
        [
            210,
            377
        ],
        [
            211,
            378
        ],
        [
            211,
            378
        ],
        [
            212,
            380
        ],
        [
            212,
            380
        ],
        [
            213,
            381
        ],
        [
            213,
            381
        ],
        [
            215,
            383
        ],
        [
            215,
            384
        ],
        [
            216,
            384
        ],
        [
            217,
            386
        ],
        [
            218,
            386
        ],
        [
            218,
            387
        ],
        [
            219,
            388
        ],
        [
            219,
            389
        ],
        [
            220,
            389
        ],
        [
            220,
            390
        ],
        [
            221,
            391
        ],
        [
            223,
            393
        ],
        [
            227,
            394
        ],
        [
            230,
            396
        ],
        [
            232,
            399
        ],
        [
            234,
            399
        ],
        [
            234,
            400
        ],
        [
            235,
            401
        ],
        [
            238,
            401
        ],
        [
            239,
            402
        ],
        [
            244,
            403
        ],
        [
            248,
            404
        ],
        [
            248,
            404
        ],
        [
            249,
            404
        ],
        [
            252,
            404
        ],
        [
            255,
            403
        ],
        [
            256,
            403
        ],
        [
            257,
            402
        ],
        [
            257,
            401
        ],
        [
            258,
            400
        ],
        [
            259,
            399
        ],
        [
            259,
            398
        ],
        [
            260,
            398
        ],
        [
            260,
            398
        ],
        [
            261,
            397
        ],
        [
            262,
            396
        ],
        [
            262,
            396
        ],
        [
            263,
            395
        ],
        [
            263,
            395
        ],
        [
            264,
            395
        ],
        [
            264,
            394
        ],
        [
            266,
            392
        ],
        [
            267,
            392
        ],
        [
            268,
            390
        ],
        [
            270,
            388
        ],
        [
            270,
            387
        ],
        [
            272,
            385
        ],
        [
            272,
            383
        ],
        [
            272,
            381
        ],
        [
            272,
            378
        ],
        [
            272,
            375
        ],
        [
            272,
            373
        ],
        [
            272,
            372
        ],
        [
            272,
            371
        ],
        [
            272,
            370
        ],
        [
            272,
            369
        ],
        [
            272,
            369
        ],
        [
            272,
            368
        ],
        [
            272,
            367
        ],
        [
            272,
            365
        ],
        [
            272,
            364
        ],
        [
            271,
            362
        ],
        [
            271,
            361
        ],
        [
            270,
            360
        ],
        [
            270,
            357
        ],
        [
            269,
            356
        ],
        [
            269,
            354
        ],
        [
            268,
            352
        ],
        [
            268,
            348
        ],
        [
            267,
            348
        ],
        [
            267,
            346
        ],
        [
            267,
            344
        ],
        [
            267,
            341
        ],
        [
            267,
            339
        ],
        [
            267,
            338
        ],
        [
            267,
            337
        ],
        [
            267,
            337
        ],
        [
            267,
            335
        ],
        [
            267,
            333
        ],
        [
            267,
            332
        ],
        [
            267,
            330
        ],
        [
            267,
            329
        ],
        [
            267,
            326
        ],
        [
            267,
            324
        ],
        [
            267,
            323
        ],
        [
            267,
            322
        ],
        [
            267,
            320
        ],
        [
            267,
            318
        ],
        [
            267,
            317
        ],
        [
            267,
            315
        ],
        [
            267,
            313
        ],
        [
            267,
            312
        ],
        [
            268,
            311
        ],
        [
            268,
            310
        ],
        [
            268,
            309
        ],
        [
            268,
            309
        ],
        [
            268,
            308
        ],
        [
            268,
            307
        ],
        [
            270,
            306
        ],
        [
            270,
            306
        ],
        [
            271,
            305
        ],
        [
            271,
            305
        ],
        [
            273,
            305
        ],
        [
            273,
            305
        ],
        [
            275,
            305
        ],
        [
            275,
            305
        ],
        [
            276,
            305
        ],
        [
            276,
            304
        ],
        [
            277,
            304
        ],
        [
            277,
            303
        ],
        [
            277,
            302
        ],
        [
            278,
            300
        ],
        [
            278,
            299
        ],
        [
            278,
            299
        ]
    ],
    "junction_points": [
        [
            177,
            292
        ],
        [
            88,
            295
        ],
        [
            89,
            295
        ],
        [
            90,
            295
        ],
        [
            89,
            296
        ],
        [
            90,
            296
        ],
        [
            278,
            300
        ],
        [
            278,
            301
        ],
        [
            185,
            303
        ],
        [
            186,
            303
        ],
        [
            95,
            304
        ],
        [
            185,
            304
        ],
        [
            186,
            304
        ],
        [
            95,
            305
        ],
        [
            96,
            305
        ],
        [
            186,
            305
        ],
        [
            95,
            306
        ],
        [
            96,
            306
        ],
        [
            66,
            316
        ],
        [
            67,
            316
        ],
        [
            97,
            316
        ],
        [
            98,
            316
        ],
        [
            66,
            317
        ],
        [
            67,
            317
        ],
        [
            97,
            317
        ],
        [
            98,
            317
        ],
        [
            66,
            318
        ],
        [
            65,
            319
        ],
        [
            101,
            328
        ],
        [
            58,
            330
        ],
        [
            58,
            331
        ],
        [
            103,
            334
        ],
        [
            103,
            335
        ],
        [
            104,
            335
        ],
        [
            56,
            336
        ],
        [
            103,
            336
        ],
        [
            104,
            336
        ],
        [
            55,
            337
        ],
        [
            56,
            337
        ],
        [
            104,
            337
        ],
        [
            55,
            338
        ],
        [
            56,
            338
        ],
        [
            55,
            339
        ],
        [
            105,
            339
        ],
        [
            54,
            340
        ],
        [
            105,
            340
        ],
        [
            106,
            340
        ],
        [
            53,
            341
        ],
        [
            105,
            341
        ],
        [
            106,
            341
        ],
        [
            52,
            342
        ],
        [
            53,
            342
        ],
        [
            52,
            343
        ],
        [
            53,
            343
        ],
        [
            52,
            344
        ],
        [
            193,
            344
        ],
        [
            193,
            345
        ],
        [
            194,
            345
        ],
        [
            193,
            346
        ],
        [
            194,
            346
        ],
        [
            194,
            347
        ],
        [
            195,
            347
        ],
        [
            110,
            348
        ],
        [
            111,
            348
        ],
        [
            194,
            348
        ],
        [
            195,
            348
        ],
        [
            110,
            349
        ],
        [
            111,
            349
        ],
        [
            195,
            349
        ],
        [
            111,
            350
        ],
        [
            112,
            350
        ],
        [
            111,
            351
        ],
        [
            112,
            351
        ],
        [
            50,
            352
        ],
        [
            112,
            352
        ],
        [
            112,
            353
        ],
        [
            113,
            353
        ],
        [
            112,
            354
        ],
        [
            113,
            354
        ],
        [
            113,
            355
        ],
        [
            113,
            356
        ],
        [
            114,
            356
        ],
        [
            113,
            357
        ],
        [
            114,
            357
        ],
        [
            48,
            358
        ],
        [
            114,
            358
        ],
        [
            200,
            358
        ],
        [
            200,
            359
        ],
        [
            201,
            359
        ],
        [
            115,
            360
        ],
        [
            200,
            360
        ],
        [
            201,
            360
        ],
        [
            201,
            361
        ],
        [
            202,
            361
        ],
        [
            116,
            362
        ],
        [
            201,
            362
        ],
        [
            202,
            362
        ],
        [
            202,
            363
        ],
        [
            119,
            367
        ],
        [
            204,
            367
        ],
        [
            119,
            368
        ],
        [
            120,
            368
        ],
        [
            204,
            368
        ],
        [
            205,
            368
        ],
        [
            119,
            369
        ],
        [
            120,
            369
        ],
        [
            204,
            369
        ],
        [
            205,
            369
        ],
        [
            44,
            370
        ],
        [
            120,
            370
        ],
        [
            205,
            370
        ],
        [
            43,
            371
        ],
        [
            44,
            371
        ],
        [
            43,
            372
        ],
        [
            44,
            372
        ],
        [
            121,
            372
        ],
        [
            43,
            373
        ],
        [
            42,
            374
        ],
        [
            122,
            374
        ],
        [
            41,
            375
        ],
        [
            42,
            375
        ],
        [
            41,
            376
        ],
        [
            42,
            376
        ],
        [
            123,
            376
        ],
        [
            124,
            378
        ],
        [
            125,
            379
        ],
        [
            125,
            380
        ],
        [
            126,
            380
        ],
        [
            125,
            381
        ],
        [
            126,
            381
        ],
        [
            40,
            383
        ],
        [
            129,
            385
        ],
        [
            129,
            386
        ],
        [
            271,
            386
        ],
        [
            270,
            387
        ],
        [
            34,
            388
        ],
        [
            35,
            388
        ],
        [
            270,
            388
        ],
        [
            32,
            389
        ],
        [
            33,
            389
        ],
        [
            34,
            389
        ],
        [
            35,
            389
        ],
        [
            30,
            390
        ],
        [
            31,
            390
        ],
        [
            32,
            390
        ],
        [
            33,
            390
        ],
        [
            30,
            391
        ],
        [
            31,
            391
        ],
        [
            235,
            400
        ],
        [
            236,
            400
        ],
        [
            235,
            401
        ],
        [
            236,
            401
        ],
        [
            237,
            401
        ],
        [
            158,
            402
        ],
        [
            241,
            402
        ],
        [
            242,
            402
        ],
        [
            157,
            403
        ],
        [
            158,
            403
        ],
        [
            241,
            403
        ],
        [
            242,
            403
        ],
        [
            253,
            403
        ],
        [
            254,
            403
        ],
        [
            253,
            404
        ],
        [
            254,
            404
        ]
    ],
    "curvature_profile": [
        -45.0,
        0.0,
        0.0,
        0.0,
        0.0,
        0.0,
        0.0,
        0.0,
        0.0,
        0.0,
        0.0,
        0.0,
        0.0,
        -90.0,
        90.0,
        -45.0,
        0.0,
        26.56505117707799,
        18.43494882292201,
        -90.0,
        71.56505117707799,
        -26.56505117707799,
        0.0,
        0.0,
        -45.0,
        90.0,
        -90.0,
        45.0,
        -45.0,
        90.0,
        -90.0,
        90.0,
        -90.0,
        0.0,
        18.43494882292201,
        8.13010235415598,
        18.43494882292201,
        -45.0,
        45.0,
        45.0,
        -90.0,
        0.0,
        45.0,
        -45.0,
        0.0,
        45.0,
        -18.43494882292201,
        -26.56505117707799,
        90.0,
        -90.0,
        45.0,
        -45.0,
        0.0,
        0.0,
        0.0,
        0.0,
        45.0,
        0.0,
        -18.43494882292201,
        0.0,
        63.43494882292201,
        -45.0,
        -45.0,
        0.0,
        14.036243467926468,
        75.96375653207353,
        -71.56505117707799,
        8.13010235415598,
        36.86989764584402,
        -36.86989764584402,
        0.0,
        7.125016348901795,
        -33.690067525979785,
        63.43494882292201,
        -45.0,
        26.56505117707799,
        0.0,
        0.0,
        -26.56505117707799,
        71.56505117707799,
        -90.0,
        90.0,
        -90.0,
        45.0,
        23.19859051364819,
        -68.19859051364818,
        71.56505117707799,
        -26.56505117707799,
        56.309932474020215,
        45.0,
        33.690067525979785,
        -14.036243467926468,
        -75.96375653207353,
        0.0,
        90.0,
        0.0,
        -26.56505117707799,
        26.56505117707799,
        0.0,
        0.0,
        -18.43494882292201,
        18.43494882292201,
        -45.0,
        45.0,
        -26.56505117707799,
        26.56505117707799,
        -26.56505117707799,
        26.56505117707799,
        -33.690067525979785,
        19.653824058053317,
        -19.653824058053317,
        0.0,
        0.0,
        15.255118703057775,
        0.0,
        0.0,
        -8.13010235415598,
        0.0,
        -63.43494882292201,
        45.0,
        45.0,
        -45.0,
        45.0,
        -45.0,
        11.309932474020215,
        33.690067525979785,
        -45.0,
        18.43494882292201,
        0.0,
        -7.125016348901795,
        -11.309932474020215,
        45.0,
        -45.0,
        11.309932474020215,
        -56.309932474020215,
        90.0,
        -90.0,
        90.0,
        -90.0,
        45.0,
        -45.0,
        45.0,
        -18.43494882292201,
        63.43494882292201,
        -45.0,
        -45.0,
        63.43494882292201,
        -63.43494882292201,
        45.0,
        45.0,
        -90.0,
        0.0,
        0.0,
        0.0,
        0.0,
        0.0,
        0.0,
        0.0,
        0.0,
        0.0,
        0.0,
        -45.0,
        -45.0,
        45.0,
        -45.0,
        90.0,
        -90.0,
        0.0,
        0.0,
        0.0,
        45.0,
        -45.0,
        0.0,
        0.0,
        0.0,
        0.0,
        0.0,
        0.0,
        0.0,
        0.0,
        0.0,
        0.0,
        0.0,
        0.0,
        90.0,
        -90.0,
        0.0,
        0.0,
        0.0,
        0.0,
        0.0,
        0.0,
        0.0,
        0.0,
        0.0,
        0.0,
        0.0,
        0.0,
        0.0,
        0.0,
        90.0,
        -90.0,
        0.0,
        0.0,
        0.0,
        90.0,
        -90.0,
        0.0,
        -26.56505117707799,
        26.56505117707799,
        0.0,
        0.0,
        0.0,
        0.0,
        0.0,
        0.0,
        0.0,
        0.0,
        0.0,
        0.0,
        90.0,
        -90.0,
        0.0,
        0.0,
        0.0,
        0.0,
        90.0,
        -90.0,
        0.0,
        45.0,
        4.398705354995528,
        22.166345822082462,
        -71.56505117707799,
        45.0,
        45.0,
        0.0,
        -90.0,
        90.0,
        26.56505117707799,
        18.43494882292201,
        45.0,
        -63.43494882292201,
        18.43494882292201,
        30.963756532073532,
        -4.398705354995542,
        -8.13010235415598,
        26.56505117707799,
        0.0,
        -26.56505117707799,
        26.56505117707799,
        0.0,
        0.0,
        -26.56505117707799,
        26.56505117707799,
        0.0,
        -14.036243467926468,
        14.036243467926468,
        -90.0,
        90.0,
        -90.0,
        90.0,
        0.0,
        -45.0,
        45.0,
        0.0,
        0.0,
        0.0,
        -45.0,
        26.56505117707799,
        -15.255118703057775,
        33.690067525979785,
        -26.56505117707799,
        -18.43494882292201,
        18.43494882292201,
        8.13010235415598,
        -26.56505117707799,
        18.43494882292201,
        12.528807709151522,
        -30.963756532073532,
        45.0,
        -45.0,
        -45.0,
        63.43494882292201,
        -18.43494882292201,
        -45.0,
        63.43494882292201,
        -63.43494882292201,
        45.0,
        -45.0,
        45.0,
        45.0,
        -90.0,
        63.43494882292201,
        -63.43494882292201,
        90.0,
        -45.0,
        45.0,
        -90.0,
        90.0,
        -45.0,
        0.0,
        -30.96375653207352,
        19.653824058053306,
        22.61986494804043,
        -56.309932474020215,
        90.0,
        -45.0,
        -45.0,
        45.0,
        -33.690067525979785,
        2.7263109939062655,
        -14.036243467926479,
        0.0,
        0.0,
        -18.43494882292201,
        18.43494882292201,
        -45.0,
        -45.0,
        45.0,
        0.0,
        -45.0,
        90.0,
        0.0,
        -45.0,
        0.0,
        45.0,
        -45.0,
        45.0,
        0.0,
        -90.0,
        45.0,
        45.0,
        -63.43494882292201,
        18.43494882292201,
        -45.0,
        45.0,
        -45.0,
        0.0,
        0.0,
        0.0,
        0.0,
        0.0,
        0.0,
        0.0,
        0.0,
        90.0,
        -90.0,
        0.0,
        0.0,
        0.0,
        -26.56505117707799,
        26.56505117707799,
        -45.0,
        45.0,
        -45.0,
        45.0,
        -26.56505117707799,
        26.56505117707799,
        270.0,
        -270.0,
        0.0,
        0.0,
        0.0,
        0.0,
        0.0,
        90.0,
        -90.0,
        0.0,
        0.0,
        0.0,
        0.0,
        0.0,
        0.0,
        0.0,
        0.0,
        0.0,
        0.0,
        0.0,
        0.0,
        0.0,
        0.0,
        45.0,
        -45.0,
        0.0,
        90.0,
        -90.0,
        0.0,
        63.43494882292201,
        26.56505117707799,
        -45.0,
        45.0,
        0.0,
        0.0,
        0.0,
        0.0,
        0.0,
        -90.0,
        90.0,
        -90.0,
        0.0,
        26.56505117707799,
        -26.56505117707799,
        90.0
    ],
    "overlay_image": "assets/river_metadata\\M\\m_0_overlay.png",
    "skeleton_image": "assets/river_metadata\\M\\m_0_skeleton.png",
    "readability": 0.9
}